materialistic/__init__.py
materialistic-0.0.1.dist-info/METADATA
materialistic-0.0.1.dist-info/WHEEL
materialistic-0.0.1.dist-info/top_level.txt
materialistic-0.0.1.dist-info/RECORD
